Metadata-Version: 1.0
Name: jarvis-spider
Version: 0.0.1
Summary: 新的爬虫框架
Home-page: UNKNOWN
Author: gk
Author-email: 1015295213@qq.com
License: MIT Licence
Keywords: pip,jarvis_spider
Platform: any
